{
	"banner":{
		"title1":"TOURBOX",
		"title2":"前所未有的創意軟體控制器",
		"description":"專為數位創作者而誕生",
		"buttonName": "더 알아보기",
		"bannerBg": "//r.tourboxtech.com/kr/src/images/index-banner-2.jpg",
		"mobileBannerBg": "//r.tourboxtech.com/kr/src/images/index-banner-mobile02.jpg",
		"mobileBannerBg1": "//r.tourboxtech.com/kr/src/images/index-banner-mobile02_01.jpg",
		"mobileBannerBg2": "//r.tourboxtech.com/kr/src/images/index-banner-mobile02_02.jpg",
		"mobileBannerBg3": "//r.tourboxtech.com/kr/src/images/index-banner-mobile02_03.jpg",
		"mobileBannerBg4": "//r.tourboxtech.com/kr/src/images/index-banner-mobile02_04.jpg",
		"bannerBg1": "//r.tourboxtech.com/kr/src/images/index-banner-2_01.jpg",
		"bannerBg2": "//r.tourboxtech.com/kr/src/images/index-banner-2_02.jpg",
		"bannerBg3": "//r.tourboxtech.com/kr/src/images/index-banner-2_03.jpg",
		"bannerBg4": "//r.tourboxtech.com/kr/src/images/index-banner-2_04.jpg"
	},
	"firstSection": {
		"bannerBg": "//r.tourboxtech.com/kr/src/images/index-first-seconds.jpg",
		"mobileBannerBg": "//r.tourboxtech.com/kr/src/images/index-first-seconds-mobile.png"
	},
	"updata": {
		"updataTitle": "TourBox Console 2.0버전 공식적으로 공개됩니다!",
		"updataTextMannary": "새로운 기능:",
		"updataTextDes": [
			"Lightroom에 대한 많은 최적화가 이루어졌으며 Lightroom에서 운영 환경을 크게 향상시키기 위해Lightroom 내장 기능과 새로운 사전 설정이 모두 추가되었습니다.",
			"투어 키는 사용자의 사용에 따라 자체 정의 기능가 추가",
			"다국어 디스플레이 최적화",
			"HUD 시스템에 Lightroom에 대한 HSL 프롬프트가 추가"
		],
		"updataBtnName": "다운로드 센터"
	},
	"indexNew": {
		"newTitle": "뉴스 센터",
		"newYear": "2020",
		"newMonth": "01",
		"newText": "TourBox Wins Great Success on Makuake Crowdfunding",
		"newBtnName": "More>"
	}
}